slackhistory/__init__.py
slackhistory/version.py
slackhistory/lib/__init__.py
slackhistory/lib/slack_helper.py
slackhistory/log/__init__.py
slackhistory/log/log.py
slackhistory/type/__init__.py
slackhistory/type/slack_types.py
slackhistory-0.3.7.dist-info/LICENCE
slackhistory-0.3.7.dist-info/METADATA
slackhistory-0.3.7.dist-info/WHEEL
slackhistory-0.3.7.dist-info/top_level.txt
slackhistory-0.3.7.dist-info/RECORD
