Metadata-Version: 2.1
Name: slackhistory
Version: 0.3.7
Summary: A slack helper library to get history (messages and replies) of a channel
Home-page: https://github.com/AlexFangSW/slack_history
Author: AlexFangSW
Author-email: alexfangsw@gmail.com
License: MIT
Keywords: slackhistory,slack history,slack helper
Requires-Python: >=3.11
License-File: LICENCE
Requires-Dist: slack-sdk >=3.23.0
Requires-Dist: aiohttp >=3.8.6
